gowbso/__init__.py
gowbso/writer.py
gowbso-2.0.0.dist-info/METADATA
gowbso-2.0.0.dist-info/RECORD
gowbso-2.0.0.dist-info/WHEEL
gowbso-2.0.0.dist-info/entry_points.txt
gowbso-2.0.0.dist-info/top_level.txt
